vigilancemeteo/__init__.py
vigilancemeteo/__version__.py
vigilancemeteo/constants.py
vigilancemeteo/department_weather_alert.py
vigilancemeteo/vigilance_proxy.py
vigilancemeteo-3.0.1.dist-info/LICENSE
vigilancemeteo-3.0.1.dist-info/METADATA
vigilancemeteo-3.0.1.dist-info/WHEEL
vigilancemeteo-3.0.1.dist-info/top_level.txt
vigilancemeteo-3.0.1.dist-info/RECORD
