Metadata-Version: 2.1
Name: vigilancemeteo
Version: 3.0.1
Summary: python API python to get active weather alerts fromhttp://vigilance.meteofrance.com/
Home-page: https://github.com/oncleben31/vigilancemeteo
Author: Oncleben31
Author-email: oncleben31@gmail.com
License: MIT
Platform: UNKNOWN
Classifier: License :: OSI Approved :: MIT License
Classifier: Programming Language :: Python
Classifier: Programming Language :: Python :: 2
Classifier: Programming Language :: Python :: 3.7
Classifier: Programming Language :: Python :: 3
Classifier: Programming Language :: Python :: 3.6
Requires-Python: >=2.7.0
Requires-Dist: lxml
Requires-Dist: pytz
